README.md
setup.cfg
setup.py
jiffy_sql.egg-info/PKG-INFO
jiffy_sql.egg-info/SOURCES.txt
jiffy_sql.egg-info/dependency_links.txt
jiffy_sql.egg-info/requires.txt
jiffy_sql.egg-info/top_level.txt
jiffysql/__init__.py
jiffysql/jiffy.py
jiffysql/gcp/__init__.py
jiffysql/gcp/big_query.py
jiffysql/gcp/fetch.py
jiffysql/gcp/logs.py
jiffysql/gcp/sql_config.py
jiffysql/graph/__init__.py
jiffysql/graph/dependency_graph.py
jiffysql/graph/table_node.py
jiffysql/schema/__init__.py
jiffysql/schema/logs_table.py
jiffysql/schema/validation_table.py
jiffysql/tasks/__init__.py
jiffysql/tasks/base_sql_task.py
jiffysql/tasks/sql_task.py
jiffysql/tasks/tasks.py
jiffysql/tasks/validation_task.py
jiffysql/utils/__init__.py
jiffysql/utils/format.py