Metadata-Version: 2.1
Name: jiffy-sql
Version: 0.0.11
Summary: Works out SQL file dependencies and runs them in a jiffy
Home-page: https://github.com/mjpcollins/jiffy-sql
Author: Matt Collins
License: UNKNOWN
Platform: UNKNOWN
